dfiq/__init__.py
dfiq/dfiq.py
dfiq/data/approaches/Q1001.10.yaml
dfiq/data/approaches/Q1001.11.yaml
dfiq/data/approaches/Q1001.12.yaml
dfiq/data/approaches/Q1018.10.yaml
dfiq/data/approaches/Q1018.11.yaml
dfiq/data/approaches/Q1018.12.yaml
dfiq/data/approaches/Q1019.10.yaml
dfiq/data/approaches/Q1020.10.yaml
dfiq/data/approaches/Q1024.10.yaml
dfiq/data/approaches/Q1036.10.yaml
dfiq/data/approaches/Q1036.11.yaml
dfiq/data/approaches/Q1037.10.yaml
dfiq/data/approaches/Q1037.11.yaml
dfiq/data/approaches/Q1037.12.yaml
dfiq/data/approaches/Q1074.10.yaml
dfiq/data/approaches/Q1074.11.yaml
dfiq/data/facets/F1001.yaml
dfiq/data/facets/F1002.yaml
dfiq/data/facets/F1003.yaml
dfiq/data/facets/F1004.yaml
dfiq/data/facets/F1005.yaml
dfiq/data/facets/F1006.yaml
dfiq/data/facets/F1007.yaml
dfiq/data/facets/F1008.yaml
dfiq/data/facets/F1009.yaml
dfiq/data/facets/F1010.yaml
dfiq/data/facets/F1011.yaml
dfiq/data/facets/F1012.yaml
dfiq/data/facets/F1013.yaml
dfiq/data/facets/F1014.yaml
dfiq/data/facets/F1015.yaml
dfiq/data/facets/F1016.yaml
dfiq/data/facets/F1017.yaml
dfiq/data/facets/F1018.yaml
dfiq/data/facets/F1019.yaml
dfiq/data/facets/F1020.yaml
dfiq/data/facets/F1021.yaml
dfiq/data/facets/F1022.yaml
dfiq/data/facets/F1023.yaml
dfiq/data/facets/F1024.yaml
dfiq/data/facets/F1025.yaml
dfiq/data/facets/F1026.yaml
dfiq/data/facets/F1027.yaml
dfiq/data/facets/F1028.yaml
dfiq/data/facets/F1029.yaml
dfiq/data/facets/F1030.yaml
dfiq/data/questions/Q1001.yaml
dfiq/data/questions/Q1002.yaml
dfiq/data/questions/Q1003.yaml
dfiq/data/questions/Q1004.yaml
dfiq/data/questions/Q1005.yaml
dfiq/data/questions/Q1006.yaml
dfiq/data/questions/Q1007.yaml
dfiq/data/questions/Q1008.yaml
dfiq/data/questions/Q1009.yaml
dfiq/data/questions/Q1010.yaml
dfiq/data/questions/Q1011.yaml
dfiq/data/questions/Q1012.yaml
dfiq/data/questions/Q1013.yaml
dfiq/data/questions/Q1014.yaml
dfiq/data/questions/Q1015.yaml
dfiq/data/questions/Q1016.yaml
dfiq/data/questions/Q1017.yaml
dfiq/data/questions/Q1018.yaml
dfiq-1.0.1.dist-info/LICENSE
dfiq-1.0.1.dist-info/METADATA
dfiq-1.0.1.dist-info/WHEEL
dfiq-1.0.1.dist-info/top_level.txt
dfiq-1.0.1.dist-info/RECORD
