Metadata-Version: 2.1
Name: dfiq
Version: 1.0.1
Summary: DFIQ is a collection of investigative questions and the approaches for answering them
Author-email: Ryan Benson <ryan@dfir.blog>
License: 
Project-URL: Homepage, https://dfiq.org
Project-URL: Repository, https://github.com/google/dfiq
Keywords: dfiq,forensics,dfir,investigative questions,security,digital forensics
Classifier: License :: OSI Approved :: Apache Software License
Classifier: Programming Language :: Python :: 3
Requires-Python: >=3.10
License-File: LICENSE
Requires-Dist: networkx >=3
Requires-Dist: pyyaml
Requires-Dist: jinja2
Requires-Dist: yamale
